run_main.py
run_main-1.0.1.dist-info/licenses/LICENSE
run_main-1.0.1.dist-info/METADATA
run_main-1.0.1.dist-info/WHEEL
run_main-1.0.1.dist-info/entry_points.txt
run_main-1.0.1.dist-info/top_level.txt
run_main-1.0.1.dist-info/RECORD
