Metadata-Version: 2.4
Name: run-main
Version: 1.0.1
Summary: Run _main() in .py File for Enhanced Debugging.
Author-email: Robird <RobirdLiu@Gmail.com>
License: MIT License
Project-URL: Homepage, https://github.com/Robird/run_main.py
Project-URL: Repository, https://github.com/Robird/run_main.py
Keywords: python,debug,runner,module,vscode
Classifier: Development Status :: 4 - Beta
Classifier: Intended Audience :: Developers
Classifier: License :: OSI Approved :: MIT License
Classifier: Programming Language :: Python :: 3
Classifier: Programming Language :: Python :: 3.7
Classifier: Programming Language :: Python :: 3.8
Classifier: Programming Language :: Python :: 3.9
Classifier: Programming Language :: Python :: 3.10
Classifier: Programming Language :: Python :: 3.11
Classifier: Topic :: Software Development :: Debuggers
Classifier: Topic :: Software Development :: Libraries :: Python Modules
Classifier: Topic :: Utilities
Requires-Python: >=3.7
License-File: LICENSE
Provides-Extra: dev
Requires-Dist: pytest>=7.0; extra == "dev"
Requires-Dist: pytest-cov>=4.0; extra == "dev"
Dynamic: license-file
